schemon_python_expectation/__init__.py
schemon_python_expectation/spark/__init__.py
schemon_python_expectation/spark/base/__init__.py
schemon_python_expectation/spark/base/base.py
schemon_python_expectation/spark/expectation/__init__.py
schemon_python_expectation/spark/expectation/column_expectation.py
schemon_python_expectation-0.0.2.dist-info/LICENSE
schemon_python_expectation-0.0.2.dist-info/METADATA
schemon_python_expectation-0.0.2.dist-info/WHEEL
schemon_python_expectation-0.0.2.dist-info/top_level.txt
schemon_python_expectation-0.0.2.dist-info/RECORD
