Metadata-Version: 2.1
Name: schemon-python-expectation
Version: 0.0.2
Summary: UNKNOWN
Home-page: UNKNOWN
License: Apache License 2.0
Platform: UNKNOWN
Requires-Python: >=3.9
License-File: LICENSE
Requires-Dist: pyspark==3.5.0
